gs_fastcopy/__init__.py
gs_fastcopy-1.0a6.dist-info/LICENSE
gs_fastcopy-1.0a6.dist-info/METADATA
gs_fastcopy-1.0a6.dist-info/WHEEL
gs_fastcopy-1.0a6.dist-info/top_level.txt
gs_fastcopy-1.0a6.dist-info/RECORD
